{
  "last_updated": "2025-12-17T06:00:02.607916",
  "satellites": {
    "98592": {
      "name": "DUTHSat-2",
      "norad_id": "98592",
      "tle": "1 64530U 25135C   25350.77950112  .00013484  00000-0  59851-3 0  9992\n2 64530  97.4501 102.6689 0006219 105.1746 255.0178 15.21668063 27140",
      "epoch": "2025-12-16T18:42:28.896768",
      "fetched_at": "2025-12-17T06:00:02.762758",
      "source": "satnogs"
    },
    "98530": {
      "name": "LAMARR",
      "norad_id": "98530",
      "tle": "1 98530U          25350.10860943 +.00011925 +00000+0 +60678-3 0 00292\n2 98530  97.4375  61.7892 0005940 297.4493  62.6136 15.16961925002631",
      "epoch": "2025-12-16T02:36:23.854752",
      "fetched_at": "2025-12-17T06:00:02.824338",
      "source": "satnogs"
    },
    "98529": {
      "name": "DIRAC",
      "norad_id": "98529",
      "tle": "1 98529U          25349.71004885 +.00010797 +00000+0 +54559-3 0 00242\n2 98529  97.4349  61.3991 0005145 306.1021  53.9736 15.17233595002576",
      "epoch": "2025-12-15T17:02:28.220640",
      "fetched_at": "2025-12-17T06:00:02.890587",
      "source": "satnogs"
    },
    "98518": {
      "name": "MICE-1",
      "norad_id": "98518",
      "tle": "1 98518U 25276Z   25345.50761227  .00000000  00000-0  85911-3 0 00002\n2 98518  97.4491  57.2978 0004401 288.2412 177.0173 15.17054724 01824",
      "epoch": "2025-12-11T12:10:57.700128",
      "fetched_at": "2025-12-17T06:00:02.954617",
      "source": "satnogs"
    }
  },
  "fetch_log": [
    {
      "norad_id": "98592",
      "name": "DUTHSat-2",
      "status": "success",
      "source": "satnogs",
      "timestamp": "2025-12-17T06:00:02.762761"
    },
    {
      "norad_id": "98530",
      "name": "LAMARR",
      "status": "success",
      "source": "satnogs",
      "timestamp": "2025-12-17T06:00:02.824342"
    },
    {
      "norad_id": "98529",
      "name": "DIRAC",
      "status": "success",
      "source": "satnogs",
      "timestamp": "2025-12-17T06:00:02.890590"
    },
    {
      "norad_id": "98518",
      "name": "MICE-1",
      "status": "success",
      "source": "satnogs",
      "timestamp": "2025-12-17T06:00:02.954622"
    }
  ]
}