{
  "last_updated": "2025-12-03T06:00:02.148094",
  "satellites": {
    "98592": {
      "name": "DUTHSat-2",
      "norad_id": "98592",
      "tle": "1 64530U 25135C   25336.83649212  .00012817  00000-0  57707-3 0  9996\n2 64530  97.4500  88.8689 0005733 148.1524 212.0059 15.21195216 25026",
      "epoch": "2025-12-02T20:04:32.919168",
      "fetched_at": "2025-12-03T06:00:02.243045",
      "source": "satnogs"
    },
    "98530": {
      "name": "LAMARR",
      "norad_id": "98530",
      "tle": "1 98530U 00000AD  25336.40952060  .00000000  00000-0  28781-3 0    02\n2 98530  97.4393  48.2275 0005848   7.4340 124.9212 15.16642069    04",
      "epoch": "2025-12-02T09:49:42.579840",
      "fetched_at": "2025-12-03T06:00:02.305118",
      "source": "satnogs"
    },
    "98529": {
      "name": "DIRAC",
      "norad_id": "98529",
      "tle": "1 98529U 00000AD  25336.40952060  .00000000  00000-0  28781-3 0    00\n2 98529  97.4363  48.2275 0005848   7.4340 124.9212 15.16642069    09",
      "epoch": "2025-12-02T09:49:42.579840",
      "fetched_at": "2025-12-03T06:00:02.350850",
      "source": "satnogs"
    },
    "98518": {
      "name": "MICE-1",
      "norad_id": "98518",
      "tle": "1 98518C 25276Z   25332.82022451 -.00006635  00000+0 -34088-3 0    02\n2 98518  97.4521  44.8306 0005282 340.9975   7.9865 15.16561278    18",
      "epoch": "2025-11-28T19:41:07.397664",
      "fetched_at": "2025-12-03T06:00:02.403467",
      "source": "satnogs"
    }
  },
  "fetch_log": [
    {
      "norad_id": "98592",
      "name": "DUTHSat-2",
      "status": "success",
      "source": "satnogs",
      "timestamp": "2025-12-03T06:00:02.243048"
    },
    {
      "norad_id": "98530",
      "name": "LAMARR",
      "status": "success",
      "source": "satnogs",
      "timestamp": "2025-12-03T06:00:02.305121"
    },
    {
      "norad_id": "98529",
      "name": "DIRAC",
      "status": "success",
      "source": "satnogs",
      "timestamp": "2025-12-03T06:00:02.350853"
    },
    {
      "norad_id": "98518",
      "name": "MICE-1",
      "status": "success",
      "source": "satnogs",
      "timestamp": "2025-12-03T06:00:02.403477"
    }
  ]
}